pyembc/__init__.py
pyembc/_pyembc.py
pyembc-0.0.1.dist-info/LICENSE
pyembc-0.0.1.dist-info/METADATA
pyembc-0.0.1.dist-info/WHEEL
pyembc-0.0.1.dist-info/top_level.txt
pyembc-0.0.1.dist-info/RECORD
