Metadata-Version: 2.1
Name: pyembc
Version: 0.0.1
Summary: pyembc - declarative c datatypes
Home-page: https://github.com/waszil/pyembc
Author: csaba.nemes
Author-email: waszil.waszil@gmail.com
License: MIT
Platform: UNKNOWN
Classifier: Programming Language :: Python :: 3
Classifier: License :: OSI Approved :: MIT License
Classifier: Operating System :: OS Independent
Requires-Python: >=3.7
